{
  "name": "Thematic Byzantine (Tagmatic Armies)",
  "version": "Warmaster Ancient Armies",
  "group": "The Dark Ages",
  "order": 8,
  "units": {
    "Kontaratoi": {
      "order": 0,
      "type": "Infantry",
      "attack": 3,
      "hits": 3,
      "armour": "5+",
      "size": 3,
      "points": 60,
      "min": 4,
      "upgrades": [
        "Extremely Heavy Infantry",
        "Varangians",
        "Thematic Decline"
      ]
    },
    "Psiloi": {
      "order": 1,
      "type": "Infantry",
      "attack": "1/1",
      "range": "15cm",
      "hits": 3,
      "size": 3,
      "points": 30,
      "max": 2,
      "specialRules": [
        "Skirmish"
      ]
    },
    "Allied Infantry": {
      "order": 2,
      "type": "Infantry",
      "attack": 3,
      "hits": 3,
      "armour": "6+",
      "size": 3,
      "points": 35,
      "max": 2,
      "specialRules": [
        "Unreliable"
      ],
      "upgrades": [
        "Rus"
      ]
    },
    "Allied Archers": {
      "order": 3,
      "type": "Infantry",
      "attack": "2/1",
      "range": "30cm",
      "hits": 3,
      "size": 3,
      "points": 30,
      "max": 2,
      "specialRules": [
        "Unreliable"
      ]
    },
    "Kavallaroi": {
      "order": 4,
      "type": "Cavalry",
      "attack": 3,
      "hits": 3,
      "armour": "5+",
      "size": 3,
      "points": 110,
      "min": 3,
      "specialRules": [
        "Shock"
      ],
      "upgrades": [
        "Elite Kavallaroi",
        "Kataphraktoi",
        "Thematic Decline"
      ]
    },
    "Light Kavallaroi": {
      "order": 5,
      "type": "Cavalry",
      "attack": "2/1",
      "range": "15cm",
      "hits": 3,
      "armour": "6+",
      "size": 3,
      "points": 60,
      "max": 1,
      "specialRules": [
        "Skirmish"
      ]
    },
    "Allied Light Cavalry": {
      "order": 6,
      "type": "Cavalry",
      "attack": "2/1",
      "range": "15cm",
      "hits": 3,
      "armour": "6+",
      "size": 3,
      "points": 50,
      "max": 1,
      "specialRules": [
        "Skirmish",
        "Unreliable"
      ]
    },
    "Allied Heavy Cavalry": {
      "order": 7,
      "type": "Cavalry",
      "attack": 3,
      "hits": 3,
      "armour": "5+",
      "size": 3,
      "points": 100,
      "max": 1,
      "specialRules": [
        "Unreliable",
        "Shock"
      ]
    },
    "Domestikos": {
      "order": 8,
      "type": "General",
      "attack": "+2",
      "command": 9,
      "size": 1,
      "points": 125,
      "armyMin": 1,
      "armyMax": 1,
      "upgrades": [
        "Portents"
      ]
    },
    "Leader": {
      "order": 9,
      "type": "Leader",
      "attack": "+1",
      "command": 8,
      "size": 1,
      "points": 80,
      "max": 2
    }
  },
  "upgrades": {
    "Extremely Heavy Infantry": {
      "order": 0,
      "type": "Infantry",
      "attack": 3,
      "hits": 3,
      "armour": "4+",
      "size": 3,
      "points": "+15",
      "specialRules": [
        "Slow"
      ]
    },
    "Elite Kavallaroi": {
      "order": 1,
      "type": "Cavalry",
      "attack": 4,
      "hits": 3,
      "armour": "5+",
      "size": 3,
      "points": "+10",
      "max": "Up to Half",
      "specialRules": [
        "Shock"
      ],
      "requiredUnits": [
        "Kavallaroi"
      ]
    },
    "Kataphraktoi": {
      "order": 2,
      "type": "Cavalry",
      "attack": 4,
      "hits": 3,
      "armour": "4+",
      "size": 3,
      "points": "+25",
      "armyMax": 1
    },
    "Rus": {
      "order": 3,
      "type": "Infantry",
      "attack": 3,
      "hits": 3,
      "armour": "6+",
      "size": 3,
      "points": "+15",
      "min": "All or None",
      "specialRules": [
        "Shieldwall"
      ],
      "requiredUnits": [
        "Allied Infantry"
      ]
    },
    "Varangians": {
      "order": 4,
      "type": "Infantry",
      "attack": 4,
      "hits": 3,
      "armour": "5+",
      "size": 3,
      "points": "+15",
      "armyMax": 1
    },
    "Thematic Decline": {
      "order": 5,
      "type": "Special",
      "attack": 2,
      "hits": 3,
      "armour": "5+",
      "size": 3,
      "points": "-10"
    },
    "Portents": {
      "order": 6,
      "type": "Special",
      "attack": "+0",
      "points": "+10",
      "armyMax": 1
    }
  },
  "specialRules": {
    "Skirmish": {
      "order": 1
    },
    "Unreliable": {
      "order": 2
    },
    "Shock": {
      "order": 3
    },
    "Slow": {
      "order": 4
    },
    "Shieldwall": {
      "order": 5
    },
    "Portents": {
      "order": 6
    }
  }
}